topographer/__init__.py
topographer/connection_set.py
topographer/models.py
topographer/node_set.py
topographer/ops.py
topographer/property.py
topographer/query_builder.py
topographer-0.1.0.dist-info/WHEEL
topographer-0.1.0.dist-info/METADATA
topographer-0.1.0.dist-info/RECORD
