Metadata-Version: 2.1
Name: topographer
Version: 0.1.0
Summary: 
Author: Zach Probst
Author-email: zprobst@resilientvitality.com
Requires-Python: >=3.10,<4.0
Classifier: Programming Language :: Python :: 3
Classifier: Programming Language :: Python :: 3.10
Requires-Dist: pydantic (>=1.10.2,<2.0.0)
